dbreak_sqlalchemy.py
dbreak_sqlalchemy-0.0.1.dist-info/METADATA
dbreak_sqlalchemy-0.0.1.dist-info/WHEEL
dbreak_sqlalchemy-0.0.1.dist-info/entry_points.txt
dbreak_sqlalchemy-0.0.1.dist-info/top_level.txt
dbreak_sqlalchemy-0.0.1.dist-info/RECORD
